{
    "configurations": [
        {
            "name": "Linux",
            "includePath": [
                "${workspaceFolder}/**",
                "/usr/include/lua5.3",
                "${workspaceFolder}/arena",
                "${workspaceFolder}/arena/src",
                "${workspaceFolder}/arena/src/core",
                "${workspaceFolder}/arena/external"
            ],
            "defines": [],
            "compilerPath": "/usr/bin/clang",
            "cStandard": "c17",
            "cppStandard": "c++17",
            "intelliSenseMode": "linux-clang-x64"
        }
    ],
    "version": 4
}